{
    "annotations": {
      "list": [
        {
          "builtIn": 1,
          "datasource": {
            "type": "grafana",
            "uid": "-- Grafana --"
          },
          "enable": true,
          "hide": true,
          "iconColor": "rgba(0, 211, 255, 1)",
          "name": "Annotations & Alerts",
          "target": {
            "limit": 100,
            "matchAny": false,
            "tags": [],
            "type": "dashboard"
          },
          "type": "dashboard"
        }
      ]
    },
    "editable": true,
    "fiscalYearStartMonth": 0,
    "graphTooltip": 0,
    "id": 49,
    "links": [],
    "liveNow": false,
    "panels": [
      {
        "datasource": {
          "type": "prometheus",
          "uid": "PC96415006F908B67"
        },
        "fieldConfig": {
          "defaults": {
            "color": {
              "mode": "thresholds"
            },
            "custom": {
              "align": "auto",
              "displayMode": "auto",
              "inspect": false
            },
            "mappings": [],
            "thresholds": {
              "mode": "absolute",
              "steps": [
                {
                  "color": "green",
                  "value": null
                },
                {
                  "color": "red",
                  "value": 80
                }
              ]
            }
          },
          "overrides": []
        },
        "gridPos": {
          "h": 19,
          "w": 4,
          "x": 0,
          "y": 0
        },
        "id": 2,
        "options": {
          "footer": {
            "fields": "",
            "reducer": [
              "sum"
            ],
            "show": false
          },
          "showHeader": true
        },
        "pluginVersion": "9.1.7",
        "targets": [
          {
            "datasource": {
              "type": "prometheus",
              "uid": "PC96415006F908B67"
            },
            "editorMode": "code",
            "exemplar": false,
            "expr": "count by (projectname) (sum_over_time(carbon_up{dcc=\"flame\"}[1d]))",
            "format": "table",
            "instant": true,
            "legendFormat": "__auto",
            "range": false,
            "refId": "A"
          }
        ],
        "title": "flame projects launched today",
        "transformations": [
          {
            "id": "organize",
            "options": {
              "excludeByName": {
                "Time": true,
                "Value": true
              },
              "indexByName": {},
              "renameByName": {}
            }
          }
        ],
        "type": "table"
      },
      {
        "datasource": {
          "type": "prometheus",
          "uid": "PC96415006F908B67"
        },
        "fieldConfig": {
          "defaults": {
            "color": {
              "mode": "thresholds"
            },
            "custom": {
              "align": "auto",
              "displayMode": "auto",
              "inspect": false
            },
            "mappings": [],
            "thresholds": {
              "mode": "absolute",
              "steps": [
                {
                  "color": "green",
                  "value": null
                },
                {
                  "color": "red",
                  "value": 80
                }
              ]
            }
          },
          "overrides": []
        },
        "gridPos": {
          "h": 19,
          "w": 4,
          "x": 4,
          "y": 0
        },
        "id": 3,
        "options": {
          "footer": {
            "fields": "",
            "reducer": [
              "sum"
            ],
            "show": false
          },
          "showHeader": true
        },
        "pluginVersion": "9.1.7",
        "targets": [
          {
            "datasource": {
              "type": "prometheus",
              "uid": "PC96415006F908B67"
            },
            "editorMode": "code",
            "exemplar": false,
            "expr": "count by (projectname) (sum_over_time(carbon_up{dcc=\"nuke\"}[1d]))",
            "format": "table",
            "instant": true,
            "legendFormat": "__auto",
            "range": false,
            "refId": "A"
          }
        ],
        "title": "nuke projects launched today",
        "transformations": [
          {
            "id": "organize",
            "options": {
              "excludeByName": {
                "Time": true,
                "Value": true
              },
              "indexByName": {},
              "renameByName": {}
            }
          }
        ],
        "type": "table"
      },
      {
        "datasource": {
          "type": "prometheus",
          "uid": "PC96415006F908B67"
        },
        "fieldConfig": {
          "defaults": {
            "color": {
              "mode": "thresholds"
            },
            "custom": {
              "align": "auto",
              "displayMode": "auto",
              "inspect": false
            },
            "mappings": [],
            "thresholds": {
              "mode": "absolute",
              "steps": [
                {
                  "color": "green",
                  "value": null
                },
                {
                  "color": "red",
                  "value": 80
                }
              ]
            }
          },
          "overrides": []
        },
        "gridPos": {
          "h": 19,
          "w": 4,
          "x": 8,
          "y": 0
        },
        "id": 5,
        "options": {
          "footer": {
            "fields": "",
            "reducer": [
              "sum"
            ],
            "show": false
          },
          "showHeader": true
        },
        "pluginVersion": "9.1.7",
        "targets": [
          {
            "datasource": {
              "type": "prometheus",
              "uid": "PC96415006F908B67"
            },
            "editorMode": "code",
            "exemplar": false,
            "expr": "count by (projectname) (sum_over_time(carbon_up{dcc=\"maya\"}[1d]))",
            "format": "table",
            "instant": true,
            "legendFormat": "__auto",
            "range": false,
            "refId": "A"
          }
        ],
        "title": "maya projects launched today",
        "transformations": [
          {
            "id": "organize",
            "options": {
              "excludeByName": {
                "Time": true,
                "Value": true
              },
              "indexByName": {},
              "renameByName": {}
            }
          }
        ],
        "type": "table"
      },
      {
        "datasource": {
          "type": "prometheus",
          "uid": "PC96415006F908B67"
        },
        "fieldConfig": {
          "defaults": {
            "color": {
              "mode": "thresholds"
            },
            "custom": {
              "align": "auto",
              "displayMode": "auto",
              "inspect": false
            },
            "mappings": [],
            "thresholds": {
              "mode": "absolute",
              "steps": [
                {
                  "color": "green",
                  "value": null
                },
                {
                  "color": "red",
                  "value": 80
                }
              ]
            }
          },
          "overrides": []
        },
        "gridPos": {
          "h": 19,
          "w": 4,
          "x": 12,
          "y": 0
        },
        "id": 4,
        "options": {
          "footer": {
            "fields": "",
            "reducer": [
              "sum"
            ],
            "show": false
          },
          "showHeader": true
        },
        "pluginVersion": "9.1.7",
        "targets": [
          {
            "datasource": {
              "type": "prometheus",
              "uid": "PC96415006F908B67"
            },
            "editorMode": "code",
            "exemplar": false,
            "expr": "count by (projectname) (sum_over_time(carbon_up{dcc=\"houdini\"}[1d]))",
            "format": "table",
            "instant": true,
            "legendFormat": "__auto",
            "range": false,
            "refId": "A"
          }
        ],
        "title": "flame projects launched today",
        "transformations": [
          {
            "id": "organize",
            "options": {
              "excludeByName": {
                "Time": true,
                "Value": true
              },
              "indexByName": {},
              "renameByName": {}
            }
          }
        ],
        "type": "table"
      }
    ],
    "schemaVersion": 37,
    "style": "dark",
    "tags": [],
    "templating": {
      "list": []
    },
    "time": {
      "from": "now-6h",
      "to": "now"
    },
    "timepicker": {},
    "timezone": "",
    "title": "Projects Launched",
    "uid": "08Y0PWe4z",
    "version": 1,
    "weekStart": ""
  }